{
    "version": 1.3,
    "people": {
        "person_id": -1,
        "pose_keypoints_2d": [
            950.665771484375,
            422.61602783203125,
            1.7700068950653076,
            952.9668579101562,
            469.81903076171875,
            1.7745141983032227,
            845.744384765625,
            514.4161376953125,
            1.7607792615890503,
            817.7650146484375,
            584.470947265625,
            1.4489012956619263,
            924.61083984375,
            402.39874267578125,
            1.3856606483459473,
            1064.4149169921875,
            501.0059814453125,
            1.7255020141601562,
            1081.1875,
            517.6329345703125,
            1.4011871814727783,
            985.53955078125,
            348.09576416015625,
            1.2442681789398193,
            963.5755004882812,
            876.9373779296875,
            1.5480135679244995,
            908.902587890625,
            877.7134399414062,
            1.550948143005371,
            897.512939453125,
            1243.2984619140625,
            1.387684941291809,
            897.4493408203125,
            1583.974853515625,
            1.3734947443008423,
            1018.4560546875,
            876.158447265625,
            1.5450786352157593,
            1020.87890625,
            1242.6011962890625,
            1.3869128227233887,
            1022.0587768554688,
            1583.2982177734375,
            1.3733177185058594,
            930.394775390625,
            352.48809814453125,
            1.6811752319335938,
            971.7174072265625,
            353.29083251953125,
            1.6807621717453003,
            930.394775390625,
            352.48809814453125,
            1.6811752319335938,
            971.7174072265625,
            353.29083251953125,
            1.6807621717453003,
            1036.91064453125,
            1796.858642578125,
            1.2246965169906616,
            1036.91064453125,
            1796.858642578125,
            1.2246965169906616,
            1036.91064453125,
            1796.858642578125,
            1.2246965169906616,
            882.8712768554688,
            1797.690185546875,
            1.2250285148620605,
            882.8712768554688,
            1797.690185546875,
            1.2250285148620605,
            882.8712768554688,
            1797.690185546875,
            1.2250285148620605
        ],
        "face_keypoints_2d": [
            0,
            0,
            0,
            0,
            0,
            0,
            0,
            0,
            0,
            0,
            0,
            0,
            0,
            0,
            0,
            0,
            0,
            0,
            0,
            0,
            0,
            0,
            0,
            0,
            0,
            0,
            0,
            0,
            0,
            0,
            0,
            0,
            0,
            0,
            0,
            0,
            0,
            0,
            0,
            0,
            0,
            0,
            0,
            0,
            0,
            0,
            0,
            0,
            0,
            0,
            0,
            0,
            0,
            0,
            0,
            0,
            0,
            0,
            0,
            0,
            0,
            0,
            0,
            0,
            0,
            0,
            0,
            0,
            0,
            0,
            0,
            0,
            0,
            0,
            0,
            0,
            0,
            0,
            0,
            0,
            0,
            0,
            0,
            0,
            0,
            0,
            0,
            0,
            0,
            0,
            0,
            0,
            0,
            0,
            0,
            0,
            0,
            0,
            0,
            0,
            0,
            0,
            0,
            0,
            0,
            0,
            0,
            0,
            0,
            0,
            0,
            0,
            0,
            0,
            0,
            0,
            0,
            0,
            0,
            0,
            0,
            0,
            0,
            0,
            0,
            0,
            0,
            0,
            0,
            0,
            0,
            0,
            0,
            0,
            0,
            0,
            0,
            0,
            0,
            0,
            0,
            0,
            0,
            0,
            0,
            0,
            0,
            0,
            0,
            0,
            0,
            0,
            0,
            0,
            0,
            0,
            0,
            0,
            0,
            0,
            0,
            0,
            0,
            0,
            0,
            0,
            0,
            0,
            0,
            0,
            0,
            0,
            0,
            0,
            0,
            0,
            0,
            0,
            0,
            0,
            0,
            0,
            0,
            0,
            0,
            0,
            0,
            0,
            0,
            0,
            0,
            0,
            0,
            0,
            0,
            0,
            0,
            0,
            0,
            0,
            0,
            0,
            0,
            0,
            0,
            0,
            0,
            0,
            0,
            0
        ],
        "hand_left_keypoints_2d": [
            985.53955078125,
            348.09576416015625,
            1.2442681789398193,
            974.34228515625,
            327.19866943359375,
            1.2650140523910522,
            959.573974609375,
            285.4556884765625,
            1.2878388166427612,
            952.2879638671875,
            263.5433349609375,
            1.3083525896072388,
            947.690185546875,
            247.5362548828125,
            1.3329477310180664,
            970.704345703125,
            247.0709228515625,
            1.2474721670150757,
            927.806640625,
            250.07830810546875,
            1.2446489334106445,
            944.7955932617188,
            268.20501708984375,
            1.2495195865631104,
            966.3255004882812,
            287.609619140625,
            1.2550451755523682,
            971.0567016601562,
            244.28326416015625,
            1.2246826887130737,
            925.7645263671875,
            254.2254638671875,
            1.2248270511627197,
            945.6913452148438,
            275.7486572265625,
            1.2308098077774048,
            971.2283935546875,
            284.84173583984375,
            1.234186053276062,
            972.2581176757812,
            247.7218017578125,
            1.2039616107940674,
            930.2846069335938,
            256.43292236328125,
            1.2055714130401611,
            948.4535522460938,
            278.90899658203125,
            1.213793158531189,
            968.6967163085938,
            291.1785888671875,
            1.218663215637207,
            971.9629516601562,
            255.57452392578125,
            1.1865730285644531,
            968.6749877929688,
            221.5858154296875,
            1.165749192237854,
            967.0886840820312,
            203.99530029296875,
            1.1552798748016357,
            965.16015625,
            180.9522705078125,
            1.141877293586731
        ],
        "hand_right_keypoints_2d": [
            924.61083984375,
            402.39874267578125,
            1.3856606483459473,
            935.29638671875,
            382.796142578125,
            1.4061119556427002,
            947.122802734375,
            343.69146728515625,
            1.4287227392196655,
            953.0777587890625,
            322.71636962890625,
            1.4490150213241577,
            956.9880981445312,
            306.83245849609375,
            1.473276138305664,
            937.118896484375,
            311.455078125,
            1.3890773057937622,
            975.4805297851562,
            314.45391845703125,
            1.3846185207366943,
            959.600341796875,
            329.8026123046875,
            1.389931559562683,
            939.6368408203125,
            346.11663818359375,
            1.3960374593734741,
            935.826416015625,
            309.88653564453125,
            1.3662925958633423,
            976.3140258789062,
            319.0078125,
            1.36472749710083,
            957.7998046875,
            337.28704833984375,
            1.3711698055267334,
            934.6494750976562,
            344.2373046875,
            1.375200629234314,
            933.8919067382812,
            313.84637451171875,
            1.345562219619751,
            971.4226684570312,
            321.7354736328125,
            1.3456370830535889,
            954.6256713867188,
            340.85968017578125,
            1.3542084693908691,
            936.220703125,
            350.92578125,
            1.3595187664031982,
            933.4569091796875,
            321.5909423828125,
            1.3280696868896484,
            938.30810546875,
            292.77374267578125,
            1.307055115699768,
            940.5928955078125,
            277.8599853515625,
            1.2965030670166016,
            943.2954711914062,
            258.3175048828125,
            1.2830126285552979
        ],
        "pose_keypoints_3d": [],
        "face_keypoints_3d": [],
        "hand_left_keypoints_3d": [],
        "hand_right_keypoints_3d": []
    },
    "camparam": {
        "Intrinsics": {
            "data": ""
        },
        "CameraMatrix": {
            "data": ""
        },
        "Distortion": {
            "rows": "",
            "data": ""
        }
    }
}